pg_environment/__init__.py
pg_environment/config.py
pg_environment/define.py
pg_environment-1.0.8.dist-info/METADATA
pg_environment-1.0.8.dist-info/WHEEL
pg_environment-1.0.8.dist-info/top_level.txt
pg_environment-1.0.8.dist-info/RECORD
